[
  {
    "html": "<div style=\"position:relative;width:100%;height:100%;background:var(--surface-dark);background-color:var(--surface-dark);overflow:hidden;\">\n            <div style=\"inset: 0; opacity: 0.04; position: absolute; pointer-events: none; z-index: 1; background: var(--texture-grain)\"></div>\n            \n            <div class=\"slide-content--bleed\" style=\"position:relative;z-index:10;padding:0;display:flex;flex-direction:column;justify-content:stretch;height:100%;width:100%;box-sizing:border-box;overflow:hidden;\">\n                <div style=\"position:relative;width:100%;height:100%;\">\n            <div style=\"position:relative;width:100%;height:100%;border-radius: 0;overflow:hidden;background:transparent;box-sizing:border-box;\">\n                <img src=\"https://images.unsplash.com/photo-1519389950473-47ba0277781c?w=600\" alt=\"Inside the Nexus Rendering Pipeline\" style=\"display:block;width:100%;height:100%;object-fit: cover; object-position: center;filter: contrast(1.06) brightness(1.06);\" />\n                <div style=\"position:absolute;inset:0;background:linear-gradient(to bottom, rgba(0,0,0,0.15), rgba(0,0,0,0.68));z-index:2;\"></div>\n            </div>\n            <div style=\"position:absolute;inset:0;padding:60px 28px;display:flex;flex-direction:column;justify-content:flex-end;z-index:3;\">\n                <h2 style=\"font-family:Playfair Display;font-size:32px;font-weight:800;color:white;margin:0;line-height:1.15;letter-spacing:-0.02em;text-shadow:0 2px 10px rgba(0,0,0,0.7);\">Inside the Nexus Rendering Pipeline</h2>\n                <p style=\"font-family:DM Sans;font-size:13.5px;color:rgba(255,255,255,0.88);margin:10px 0 0;line-height:1.45;text-shadow:0 2px 8px rgba(0,0,0,0.6);\">How a one-sentence brief becomes a 10-slide carousel in under 60 seconds.</p>\n            </div>\n        </div>\n            </div>\n        </div>",
    "background": "dark",
    "variant": "bottom",
    "theme": "editorial",
    "archetype": "thought_leader",
    "slide_type": "image_headline"
  },
  {
    "html": "<div style=\"position:relative;width:100%;height:100%;background:radial-gradient(at 40% 20%, #C6282815 0px, transparent 50%), radial-gradient(at 80% 0%, #0088A610 0px, transparent 50%), radial-gradient(at 0% 50%, #FF978A12 0px, transparent 50%), var(--surface-light);background-color:var(--surface-light);overflow:hidden;\">\n            <div style=\"inset: 0; pointer-events: none; position: absolute; opacity: 0.04; background: var(--texture-grain); z-index: 1\"></div>\n            \n            <div class=\"slide-content\" style=\"position:relative;z-index:10;padding:80px var(--space-6) 80px;display:flex;flex-direction:column;justify-content:center;height:100%;width:100%;box-sizing:border-box;overflow:hidden;\">\n                <div style=\"width:100%;display:flex;flex-direction:column;gap:12px;\">\n            <h2 style=\"font-family: Playfair Display; font-size: 25px; font-weight: 600; line-height: 1.12; color: #0F0A09; margin: 0 0 12px; text-align: left; letter-spacing: -0.015em; overflow-wrap: break-word\">What Happens in 60 Seconds</h2>\n            <div style=\"display:flex;flex-direction:column;gap:10px;width:100%;border-left:3px solid #C62828;padding-left:14px;box-sizing:border-box;\"><div style=\"min-width:0;background:rgba(255,255,255,0.92);border:1px solid #D4C7C5;border-radius:0;padding:12px 14px;box-sizing:border-box;display:flex;flex-direction:column;gap:3px;position:relative;\">\n                <div style=\"display:flex;align-items:center;gap:6px;\">\n                    <span style=\"font-family:Playfair Display;font-size:9.5px;font-weight:900;color:#C62828;background:#C6282818;padding:2px 6px;border-radius:4px;\">PHASE 01</span>\n                    <h3 style=\"font-family:Playfair Display;font-size:13px;font-weight:800;color:#0F0A09;margin:0;line-height:1.2;\">Brief Parse</h3>\n                </div>\n                <p style=\"font-family:DM Sans;font-size:11px;color:#4A3F3E;margin:0;line-height:1.4;\">NLP extracts topic, tone, audience, and emotional arc from your description.</p>\n            </div><div style=\"min-width:0;background:rgba(255,255,255,0.92);border:1px solid #D4C7C5;border-radius:0;padding:12px 14px;box-sizing:border-box;display:flex;flex-direction:column;gap:3px;position:relative;\">\n                <div style=\"display:flex;align-items:center;gap:6px;\">\n                    <span style=\"font-family:Playfair Display;font-size:9.5px;font-weight:900;color:#C62828;background:#C6282818;padding:2px 6px;border-radius:4px;\">PHASE 02</span>\n                    <h3 style=\"font-family:Playfair Display;font-size:13px;font-weight:800;color:#0F0A09;margin:0;line-height:1.2;\">Arc Composition</h3>\n                </div>\n                <p style=\"font-family:DM Sans;font-size:11px;color:#4A3F3E;margin:0;line-height:1.4;\">Preset engine selects slide types, assigns emotional beats, and sequences the narrative.</p>\n            </div><div style=\"min-width:0;background:rgba(255,255,255,0.92);border:1px solid #D4C7C5;border-radius:0;padding:12px 14px;box-sizing:border-box;display:flex;flex-direction:column;gap:3px;position:relative;\">\n                <div style=\"display:flex;align-items:center;gap:6px;\">\n                    <span style=\"font-family:Playfair Display;font-size:9.5px;font-weight:900;color:#C62828;background:#C6282818;padding:2px 6px;border-radius:4px;\">PHASE 03</span>\n                    <h3 style=\"font-family:Playfair Display;font-size:13px;font-weight:800;color:#0F0A09;margin:0;line-height:1.2;\">Token Generation</h3>\n                </div>\n                <p style=\"font-family:DM Sans;font-size:11px;color:#4A3F3E;margin:0;line-height:1.4;\">Material Design color system generates a unique tonal palette. Typography scales auto-calculate.</p>\n            </div><div style=\"min-width:0;background:rgba(255,255,255,0.92);border:1px solid #D4C7C5;border-radius:0;padding:12px 14px;box-sizing:border-box;display:flex;flex-direction:column;gap:3px;position:relative;\">\n                <div style=\"display:flex;align-items:center;gap:6px;\">\n                    <span style=\"font-family:Playfair Display;font-size:9.5px;font-weight:900;color:#C62828;background:#C6282818;padding:2px 6px;border-radius:4px;\">PHASE 04</span>\n                    <h3 style=\"font-family:Playfair Display;font-size:13px;font-weight:800;color:#0F0A09;margin:0;line-height:1.2;\">Slide Rendering</h3>\n                </div>\n                <p style=\"font-family:DM Sans;font-size:11px;color:#4A3F3E;margin:0;line-height:1.4;\">Each slide type compiles HTML+CSS with dynamic font sizing, gradient backgrounds, and responsive layouts.</p>\n            </div><div style=\"min-width:0;background:rgba(255,255,255,0.92);border:1px solid #D4C7C5;border-radius:0;padding:12px 14px;box-sizing:border-box;display:flex;flex-direction:column;gap:3px;position:relative;\">\n                <div style=\"display:flex;align-items:center;gap:6px;\">\n                    <span style=\"font-family:Playfair Display;font-size:9.5px;font-weight:900;color:#C62828;background:#C6282818;padding:2px 6px;border-radius:4px;\">PHASE 05</span>\n                    <h3 style=\"font-family:Playfair Display;font-size:13px;font-weight:800;color:#0F0A09;margin:0;line-height:1.2;\">Carousel Assembly</h3>\n                </div>\n                <p style=\"font-family:DM Sans;font-size:11px;color:#4A3F3E;margin:0;line-height:1.4;\">Slides are stitched into a single scrollable HTML document with navigation, branding, and export hooks.</p>\n            </div></div>\n            <p style=\"font-family:DM Sans;font-size:10.5px;color:#4A3F3E;margin:4px 0 0;line-height:1.4;opacity:0.85;\">Chronological roadmap tracking SlideForge engine milestones from core compilation to headless PNG export.</p>\n        </div>\n            </div>\n        </div>",
    "background": "light",
    "variant": "vertical",
    "theme": "editorial",
    "archetype": "educator",
    "slide_type": "timeline"
  },
  {
    "html": "<div style=\"position:relative;width:100%;height:100%;background:radial-gradient(at 40% 20%, #C6282815 0px, transparent 50%), radial-gradient(at 80% 0%, #0088A610 0px, transparent 50%), radial-gradient(at 0% 50%, #FF978A12 0px, transparent 50%), var(--surface-light);background-color:var(--surface-light);overflow:hidden;\">\n            <div style=\"opacity: 0.04; pointer-events: none; inset: 0; position: absolute; z-index: 1; background: var(--texture-grain)\"></div>\n            \n            <div class=\"slide-content\" style=\"position:relative;z-index:10;padding:60px var(--space-6) 60px;display:flex;flex-direction:column;justify-content:center;height:100%;width:100%;box-sizing:border-box;overflow:hidden;\">\n                <div style=\"width:100%;display:flex;flex-direction:column;justify-content:center;align-items:flex-start;\">\n            <h2 style=\"font-family: Playfair Display; font-size: 25px; font-weight: 600; line-height: 1.12; color: #0F0A09; margin: 0 0 10px; text-align: left; letter-spacing: -0.015em; overflow-wrap: break-word\">Pipeline Artifacts</h2>\n            <div style=\"display:grid;grid-template-columns:1fr 1fr;grid-template-rows:1fr 1fr;gap:6px;height:210px;width:100%;\">\n                    <div style=\"position:relative;width:100%;height:100%;overflow:hidden;\">\n                <div style=\"position:relative;width:100%;height:100%;border-radius: 0;overflow:hidden;background:transparent;box-sizing:border-box;\">\n                <img src=\"https://images.unsplash.com/photo-1451187580459-43490279c0fa?w=600\" alt=\"Design tokens\" style=\"display:block;width:100%;height:100%;object-fit: cover; object-position: center;filter: contrast(1.02) brightness(1.02);\" />\n                \n            </div>\n                <div style=\"padding:5px 8px;background:rgba(0,0,0,0.62);position:absolute;top:8px;left:8px;max-width:calc(100% - 16px);z-index:3;color:white;font-family:DM Sans;font-size:10px;font-weight:800;text-align:left;border-radius:999px;letter-spacing:0.04em;text-transform:uppercase;white-space:nowrap;overflow:hidden;text-overflow:ellipsis;\">\n                    Design tokens\n                </div>\n            </div><div style=\"position:relative;width:100%;height:100%;overflow:hidden;\">\n                <div style=\"position:relative;width:100%;height:100%;border-radius: 0;overflow:hidden;background:transparent;box-sizing:border-box;\">\n                <img src=\"https://images.unsplash.com/photo-1518770660439-4636190af475?w=600\" alt=\"Slide JSON\" style=\"display:block;width:100%;height:100%;object-fit: cover; object-position: center;filter: contrast(1.02) brightness(1.02);\" />\n                \n            </div>\n                <div style=\"padding:5px 8px;background:rgba(0,0,0,0.62);position:absolute;top:8px;left:8px;max-width:calc(100% - 16px);z-index:3;color:white;font-family:DM Sans;font-size:10px;font-weight:800;text-align:left;border-radius:999px;letter-spacing:0.04em;text-transform:uppercase;white-space:nowrap;overflow:hidden;text-overflow:ellipsis;\">\n                    Slide JSON\n                </div>\n            </div><div style=\"position:relative;width:100%;height:100%;overflow:hidden;\">\n                <div style=\"position:relative;width:100%;height:100%;border-radius: 0;overflow:hidden;background:transparent;box-sizing:border-box;\">\n                <img src=\"https://images.unsplash.com/photo-1519389950473-47ba0277781c?w=600\" alt=\"Rendered HTML\" style=\"display:block;width:100%;height:100%;object-fit: cover; object-position: center;filter: contrast(1.02) brightness(1.02);\" />\n                \n            </div>\n                <div style=\"padding:5px 8px;background:rgba(0,0,0,0.62);position:absolute;top:8px;left:8px;max-width:calc(100% - 16px);z-index:3;color:white;font-family:DM Sans;font-size:10px;font-weight:800;text-align:left;border-radius:999px;letter-spacing:0.04em;text-transform:uppercase;white-space:nowrap;overflow:hidden;text-overflow:ellipsis;\">\n                    Rendered HTML\n                </div>\n            </div><div style=\"position:relative;width:100%;height:100%;overflow:hidden;\">\n                <div style=\"position:relative;width:100%;height:100%;border-radius: 0;overflow:hidden;background:transparent;box-sizing:border-box;\">\n                <img src=\"https://images.unsplash.com/photo-1460925895917-afdab827c52f?w=600\" alt=\"Exported PNG\" style=\"display:block;width:100%;height:100%;object-fit: cover; object-position: center;filter: contrast(1.02) brightness(1.02);\" />\n                \n            </div>\n                <div style=\"padding:5px 8px;background:rgba(0,0,0,0.62);position:absolute;top:8px;left:8px;max-width:calc(100% - 16px);z-index:3;color:white;font-family:DM Sans;font-size:10px;font-weight:800;text-align:left;border-radius:999px;letter-spacing:0.04em;text-transform:uppercase;white-space:nowrap;overflow:hidden;text-overflow:ellipsis;\">\n                    Exported PNG\n                </div>\n            </div>\n                </div>\n            <div style=\"font-family:DM Sans;font-size:11.5px;color:#4A3F3E;margin-top:10px;line-height:1.35;width:100%;opacity:0.9;\">From tokens to pixels \u2014 every intermediate step is inspectable</div>\n        </div>\n            </div>\n        </div>",
    "background": "light",
    "variant": "4-grid",
    "theme": "editorial",
    "archetype": "thought_leader",
    "slide_type": "image_gallery"
  },
  {
    "html": "<div style=\"position:relative;width:100%;height:100%;background:var(--surface-dark);background-color:var(--surface-dark);overflow:hidden;\">\n            <div style=\"opacity: 0.04; pointer-events: none; background: var(--texture-grain); z-index: 1; inset: 0; position: absolute\"></div>\n            \n            <div class=\"slide-content\" style=\"position:relative;z-index:10;padding:80px var(--space-6) 80px;display:flex;flex-direction:column;justify-content:center;height:100%;width:100%;box-sizing:border-box;overflow:hidden;\">\n                <div style=\"position:relative;width:100%;height:100%;display:flex;align-items:center;justify-content:center;box-sizing:border-box;\">\n            <div style=\"position:absolute;left:-80px;top:-80px;width:260px;height:260px;border-radius:50%;background:#C62828;opacity:0.06;filter:blur(50px);-webkit-filter:blur(50px);pointer-events:none;z-index:1;\"></div>\n            <div style=\"position:absolute;right:var(--space-5);bottom:var(--space-4);font-size:240px;opacity:0.04;pointer-events:none;z-index:1;user-select:none;transform:rotate(12deg);line-height:1;font-family:system-ui;\">\ud83d\udca1</div>\n            <div style=\"border-radius: 16px; border: 1px solid #3C282640; backdrop-filter: blur(12px); background: #050101CC; -webkit-backdrop-filter: blur(12px); border-left: 6px solid #C62828;padding:36px 32px;box-shadow: 0 8px 32px -4px #C628281f, 0 4px 6px -1px rgba(0,0,0,0.08), 0 2px 4px -2px rgba(0,0,0,0.05);width:100%;box-sizing:border-box;position:relative;z-index:2;\">\n                <div style=\"display:flex;align-items:center;gap:18px;margin-bottom:18px;\">\n                    <div style=\"width:44px;height:44px;min-width:44px;border-radius:50%;background:#C628281a;color:#C62828;display:flex;align-items:center;justify-content:center;font-size:20px;box-shadow:inset 0 1px 3px rgba(255,255,255,0.1);\">\ud83d\udca1</div>\n                    <div>\n                        <span style=\"font-size:9.5px;font-weight:700;letter-spacing:0.1em;text-transform:uppercase;color:#C62828;margin-bottom:4px;display:block;\">info</span>\n                        <h2 style=\"font-family:Playfair Display;font-size:20px;font-weight:800;color:#F5ECEB;margin:0;line-height:1.2;\">Zero Black Boxes</h2>\n                    </div>\n                </div>\n                <p style=\"font-family:DM Sans;font-size:16px;line-height:1.65;color:#D7CAC8;margin:0;overflow-wrap:break-word;word-break:break-word;\">Every slide JSON is inspectable. Every token is deterministic. Every rendering step is debuggable. If something looks wrong, you can trace exactly where the decision was made.</p>\n            </div>\n        </div>\n            </div>\n        </div>",
    "background": "dark",
    "variant": "info",
    "theme": "bold",
    "archetype": "thought_leader",
    "slide_type": "callout"
  },
  {
    "html": "<div style=\"position:relative;width:100%;height:100%;background:var(--surface-dark);background-color:var(--surface-dark);overflow:hidden;\">\n            <div style=\"background: var(--texture-grain); position: absolute; z-index: 1; opacity: 0.04; inset: 0; pointer-events: none\"></div>\n            <div style=\"position:absolute;inset:0;overflow:hidden;pointer-events:none;z-index:1;\"><div style=\"height: 320px; width: 320px; left: -80px; top: -80px; position: absolute; background: #C62828; pointer-events: none; border-radius: 50%; opacity: 0.07\"></div><div style=\"left: auto; transform: rotate(60deg); right: -40px; background: #0088A6; opacity: 0.05; top: 60%; pointer-events: none; position: absolute; height: 120px; border-radius: 4px; width: 120px\"></div></div>\n            <div class=\"slide-content\" style=\"position:relative;z-index:10;padding:80px var(--space-6) 80px;display:flex;flex-direction:column;justify-content:center;height:100%;width:100%;box-sizing:border-box;overflow:hidden;\">\n                <div style=\"display:flex;flex-direction:column;align-items:center;justify-content:center;text-align:center;width:100%;max-width:340px;margin:0 auto;box-sizing:border-box;\"><div style=\"font-family:DM Sans;font-size:10px;font-weight:800;color:#EE514A;background:#EE514A18;border:1px solid #EE514A40;padding:4px 12px;border-radius:20px;letter-spacing:0.08em;text-transform:uppercase;margin-bottom:12px;\">\u26a1 PRESENTATION ENGINE</div><span style=\"background: linear-gradient(135deg, #FFFFFF 0%, #F5ECEB 100%); -webkit-background-clip: text; -webkit-text-fill-color: transparent; background-clip: text; font-family: Playfair Display; font-size: 31px; font-weight: 600; line-height: 1.08; text-align: center; margin: 0 0 12px; display: block; letter-spacing: -0.02em\">Transparent by Design</span><p style=\"font-family:DM Sans;font-size:12px;color:#D7CAC8;line-height:1.45;margin:0 0 20px;max-width:320px;text-align:center;opacity:0.85;\">Full architecture documentation, API reference, and extension guides.</p><a href=\"https://slideforge.dev/docs\" style=\"display: inline-block; padding: 16px 40px; background: #FF978A; color: #050101; font-family: DM Sans; font-size: 16px; font-weight: 600; border-radius: 9999px; text-decoration: none; box-shadow: 0 4px 14px #91000040; letter-spacing: 0.02em; margin: 0 0 14px;\">Read the Docs</a><div style=\"font-family:DM Sans;font-size:11px;font-weight:600;color:#D7CAC8;margin-top:2px;opacity:0.85;letter-spacing:0.02em;\">\ud83d\udd17 github.com/ishan-parihar/slideforge-rust</div></div>\n            </div>\n        </div>",
    "background": "dark",
    "variant": "centered",
    "theme": "editorial",
    "archetype": "thought_leader",
    "slide_type": "cta",
    "validation": {
      "warnings": [
        "A plain 'cta' slide with a web button will not be interactive on Instagram/TikTok carousels. Consider using 'qr_destination' for direct conversions, or framing as a 'Link in Bio' instruction."
      ]
    }
  }
]